spacy_entity_linker/DatabaseConnection.py
spacy_entity_linker/EntityCandidates.py
spacy_entity_linker/EntityClassifier.py
spacy_entity_linker/EntityCollection.py
spacy_entity_linker/EntityElement.py
spacy_entity_linker/EntityLinker.py
spacy_entity_linker/TermCandidate.py
spacy_entity_linker/TermCandidateExtractor.py
spacy_entity_linker/__init__.py
spacy_entity_linker/__main__.py
spacy_entity_linker-1.0.1.dist-info/METADATA
spacy_entity_linker-1.0.1.dist-info/WHEEL
spacy_entity_linker-1.0.1.dist-info/entry_points.txt
spacy_entity_linker-1.0.1.dist-info/top_level.txt
spacy_entity_linker-1.0.1.dist-info/zip-safe
spacy_entity_linker-1.0.1.dist-info/RECORD
