Metadata-Version: 2.1
Name: spacy-entity-linker
Version: 1.0.1
Summary: Linked Entity Pipeline for spaCy
Home-page: https://github.com/egerber/spacy-entity-linker
Author: Emanuel Gerber
Author-email: emanuel.j.gerber@gmail.com
License: MIT
Platform: UNKNOWN
Classifier: Environment :: Console
Classifier: Intended Audience :: Developers
Classifier: Intended Audience :: Science/Research
Classifier: License :: OSI Approved :: MIT License
Classifier: Programming Language :: Cython
Classifier: Programming Language :: Python
Classifier: Programming Language :: Python :: 3.6
Requires-Dist: spacy (>=3.0.0)
Requires-Dist: numpy (>=1.0.0)
